ir_trove-0.0.2.dist-info/licenses/LICENSE
trove/__init__.py
trove/cache_manager.py
trove/config.py
trove/file_utils.py
trove/logging_utils.py
trove/trainer.py
trove/commands/__init__.py
trove/commands/env.py
trove/commands/trove_cli.py
trove/containers/__init__.py
trove/containers/container_utils.py
trove/containers/key_to_row_indices.py
trove/containers/lmdb_dict.py
trove/containers/materialized_qrel.py
trove/containers/materialized_qrel_config.py
trove/containers/result_heapq.py
trove/containers/result_heapq_fast.py
trove/containers/rows_by_key.py
trove/data/__init__.py
trove/data/collator.py
trove/data/data_args.py
trove/data/file_reader.py
trove/data/file_reader_functions.py
trove/data/file_transforms.py
trove/data/ir_dataset_binary.py
trove/data/ir_dataset_multilevel.py
trove/data/ir_encoding_dataset.py
trove/data/polars_transforms.py
trove/data/vector_cache_mixin.py
trove/evaluation/__init__.py
trove/evaluation/callback_wandb.py
trove/evaluation/evaluation_args.py
trove/evaluation/evaluator.py
trove/evaluation/evaluator_mixin_utils.py
trove/evaluation/infinite_barrier.py
trove/evaluation/metric_utils.py
trove/evaluation/metrics.py
trove/evaluation/mrr.py
trove/evaluation/relevance_evaluator.py
trove/modeling/__init__.py
trove/modeling/encoder_contriever.py
trove/modeling/encoder_default.py
trove/modeling/loss_base.py
trove/modeling/losses.py
trove/modeling/model_args.py
trove/modeling/modeling_utils.py
trove/modeling/pretrained_encoder.py
trove/modeling/pretrained_retriever.py
trove/modeling/retriever_biencoder.py
ir_trove-0.0.2.dist-info/METADATA
ir_trove-0.0.2.dist-info/WHEEL
ir_trove-0.0.2.dist-info/entry_points.txt
ir_trove-0.0.2.dist-info/top_level.txt
ir_trove-0.0.2.dist-info/RECORD
