Metadata-Version: 2.4
Name: ir-trove
Version: 0.0.2
Summary: A Flexible Toolkit for Dense Retrieval
Author-email: Reza Esfandiarpoor <reza_esfandiarpoor@brown.edu>
License-Expression: Apache-2.0
Project-URL: Homepage, https://github.com/BatsResearch/trove
Project-URL: Issues, https://github.com/BatsResearch/trove/issues
Classifier: Programming Language :: Python :: 3
Classifier: Operating System :: OS Independent
Requires-Python: >=3.10
License-File: LICENSE
Requires-Dist: datasets>=2.7.0
Requires-Dist: accelerate
Requires-Dist: huggingface_hub
Requires-Dist: numpy>=1.26.0
Requires-Dist: polars>=1.13.0
Requires-Dist: pyarrow>=16.1.0
Requires-Dist: pytrec_eval
Requires-Dist: torch>=2.0.0
Requires-Dist: tqdm
Requires-Dist: transformers>=4.43.0
Requires-Dist: peft
Requires-Dist: wandb>=0.16.0
Requires-Dist: xxhash>=3.4.0
Requires-Dist: rich
Dynamic: license-file
